pygeonhole/__init__.py
pygeonhole/__main__.py
pygeonhole/cli.py
pygeonhole/config.py
pygeonhole/database.py
pygeonhole/flags.py
pygeonhole/pygeonhole.py
pygeonhole_cli-1.0.0.dist-info/LICENSE.txt
pygeonhole_cli-1.0.0.dist-info/METADATA
pygeonhole_cli-1.0.0.dist-info/WHEEL
pygeonhole_cli-1.0.0.dist-info/entry_points.txt
pygeonhole_cli-1.0.0.dist-info/top_level.txt
pygeonhole_cli-1.0.0.dist-info/RECORD
