Metadata-Version: 2.1
Name: pygeonhole-cli
Version: 1.0.0
Summary: python cli program to organize files
Author-email: William Pol <polwilliam0@gmail.com>
License: MIT License
Project-URL: Homepage, https://github.com/betterthan-yesterday/pygeonhole-cli.git
Keywords: typer,cli,file
Classifier: License :: OSI Approved :: MIT License
Classifier: Programming Language :: Python
Classifier: Programming Language :: Python :: 3
Requires-Python: >=3.8
License-File: LICENSE.txt
Requires-Dist: typer ==0.3.2
Requires-Dist: colorama ==0.4.4
Requires-Dist: shellingham ==1.4.0
Requires-Dist: pytest ==6.2.4
